pyadb_gui/__init__.py
pyadb_gui/main.py
pyadb_gui-1.2.4.dist-info/entry_points.txt
pyadb_gui-1.2.4.dist-info/WHEEL
pyadb_gui-1.2.4.dist-info/METADATA
pyadb_gui-1.2.4.dist-info/RECORD
