Metadata-Version: 2.1
Name: pyadb-gui
Version: 1.2.4
Summary: Operate Android devices with a GUI tool producted by Python.
Author: xq
Author-email: xq_work@outlook.com
Requires-Python: >=3.7,<4.0
Classifier: Programming Language :: Python :: 3
Classifier: Programming Language :: Python :: 3.10
Classifier: Programming Language :: Python :: 3.7
Classifier: Programming Language :: Python :: 3.8
Classifier: Programming Language :: Python :: 3.9
Requires-Dist: rich (>=12.0.0,<13.0.0)
